manggee_lotto/__init__.py
manggee_lotto/draw.py
manggee_lotto-0.2.2.dist-info/METADATA
manggee_lotto-0.2.2.dist-info/WHEEL
manggee_lotto-0.2.2.dist-info/top_level.txt
manggee_lotto-0.2.2.dist-info/RECORD
