Metadata-Version: 2.1
Name: manggee_lotto
Version: 0.2.2
Summary: Default template for PDM package
Author-email: mangG907 <mang.gee@gmail.com>
License: MIT
Requires-Python: >=3.9
Requires-Dist: manggee-lotto >=0.2.0
